{"animTracks":{"instance30":[{"frame":true,"x":0,"scaleX":1,"alpha":1,"y":0,"scaleY":1,"matrix":{"c":0,"b":0,"d":1,"tx":0,"ty":0,"a":1},"rotation":0}],"instance71":[{"frame":true,"x":0,"scaleX":1,"alpha":1,"y":0,"scaleY":1,"matrix":{"c":0,"b":0,"d":1,"tx":0,"ty":0,"a":1},"rotation":0}],"instance55":[{"frame":true,"x":0,"scaleX":1,"alpha":0,"y":108,"scaleY":1,"matrix":{"c":1,"b":-1,"d":0,"tx":0,"ty":108,"a":0},"rotation":-90},{"alpha":0.109375,"matrix":{"c":1,"b":-1,"d":0,"tx":0,"ty":108,"a":0},"frame":true},{"alpha":0.22265625,"matrix":{"c":1,"b":-1,"d":0,"tx":0,"ty":108,"a":0},"frame":true},{"alpha":0.33203125,"matrix":{"c":1,"b":-1,"d":0,"tx":0,"ty":108,"a":0},"frame":true},{"alpha":0.4453125,"matrix":{"c":1,"b":-1,"d":0,"tx":0,"ty":108,"a":0},"frame":true},{"alpha":0.5546875,"matrix":{"c":1,"b":-1,"d":0,"tx":0,"ty":108,"a":0},"frame":true},{"alpha":0.66796875,"matrix":{"c":1,"b":-1,"d":0,"tx":0,"ty":108,"a":0},"frame":true},{"alpha":0.77734375,"matrix":{"c":1,"b":-1,"d":0,"tx":0,"ty":108,"a":0},"frame":true},{"alpha":0.890625,"matrix":{"c":1,"b":-1,"d":0,"tx":0,"ty":108,"a":0},"frame":true},{"alpha":1,"matrix":{"c":1,"b":-1,"d":0,"tx":0,"ty":108,"a":0},"frame":true},{"alpha":0.8984375,"matrix":{"c":1,"b":-1,"d":0,"tx":0,"ty":108,"a":0},"frame":true},{"alpha":0.80078125,"matrix":{"c":1,"b":-1,"d":0,"tx":0,"ty":108,"a":0},"frame":true},{"alpha":0.69921875,"matrix":{"c":1,"b":-1,"d":0,"tx":0,"ty":108,"a":0},"frame":true},{"alpha":0.6015625,"matrix":{"c":1,"b":-1,"d":0,"tx":0,"ty":108,"a":0},"frame":true},{"alpha":0.5,"matrix":{"c":1,"b":-1,"d":0,"tx":0,"ty":108,"a":0},"frame":true},{"alpha":0.3984375,"matrix":{"c":1,"b":-1,"d":0,"tx":0,"ty":108,"a":0},"frame":true},{"alpha":0.30078125,"matrix":{"c":1,"b":-1,"d":0,"tx":0,"ty":108,"a":0},"frame":true},{"alpha":0.19921875,"matrix":{"c":1,"b":-1,"d":0,"tx":0,"ty":108,"a":0},"frame":true},{"alpha":0.1015625,"matrix":{"c":1,"b":-1,"d":0,"tx":0,"ty":108,"a":0},"frame":true}],"instance77":[{"frame":true,"x":0,"scaleX":1,"alpha":1,"y":0,"scaleY":1,"matrix":{"c":0,"b":0,"d":1,"tx":0,"ty":0,"a":1},"rotation":0}],"instance36":[{"frame":true,"x":0,"scaleX":1,"alpha":1,"y":0,"scaleY":1,"matrix":{"c":0,"b":0,"d":1,"tx":0,"ty":0,"a":1},"rotation":0}],"instance66":[{"frame":true,"x":106,"scaleX":1,"alpha":0,"y":2,"scaleY":1,"matrix":{"c":-1,"b":1,"d":0,"tx":106.5,"ty":2.5,"a":0},"rotation":90},{"alpha":0.109375,"matrix":{"c":-1,"b":1,"d":0,"tx":106.5,"ty":2.5,"a":0},"frame":true},{"alpha":0.22265625,"matrix":{"c":-1,"b":1,"d":0,"tx":106.5,"ty":2.5,"a":0},"frame":true},{"alpha":0.33203125,"matrix":{"c":-1,"b":1,"d":0,"tx":106.5,"ty":2.5,"a":0},"frame":true},{"alpha":0.4453125,"matrix":{"c":-1,"b":1,"d":0,"tx":106.5,"ty":2.5,"a":0},"frame":true},{"alpha":0.5546875,"matrix":{"c":-1,"b":1,"d":0,"tx":106.5,"ty":2.5,"a":0},"frame":true},{"alpha":0.66796875,"matrix":{"c":-1,"b":1,"d":0,"tx":106.5,"ty":2.5,"a":0},"frame":true},{"alpha":0.77734375,"matrix":{"c":-1,"b":1,"d":0,"tx":106.5,"ty":2.5,"a":0},"frame":true},{"alpha":0.890625,"matrix":{"c":-1,"b":1,"d":0,"tx":106.5,"ty":2.5,"a":0},"frame":true},{"alpha":1,"matrix":{"c":-1,"b":1,"d":0,"tx":106.5,"ty":2.5,"a":0},"frame":true},{"alpha":0.8984375,"matrix":{"c":-1,"b":1,"d":0,"tx":106.5,"ty":2.5,"a":0},"frame":true},{"alpha":0.80078125,"matrix":{"c":-1,"b":1,"d":0,"tx":106.5,"ty":2.5,"a":0},"frame":true},{"alpha":0.69921875,"matrix":{"c":-1,"b":1,"d":0,"tx":106.5,"ty":2.5,"a":0},"frame":true},{"alpha":0.6015625,"matrix":{"c":-1,"b":1,"d":0,"tx":106.5,"ty":2.5,"a":0},"frame":true},{"alpha":0.5,"matrix":{"c":-1,"b":1,"d":0,"tx":106.5,"ty":2.5,"a":0},"frame":true},{"alpha":0.3984375,"matrix":{"c":-1,"b":1,"d":0,"tx":106.5,"ty":2.5,"a":0},"frame":true},{"alpha":0.30078125,"matrix":{"c":-1,"b":1,"d":0,"tx":106.5,"ty":2.5,"a":0},"frame":true},{"alpha":0.19921875,"matrix":{"c":-1,"b":1,"d":0,"tx":106.5,"ty":2.5,"a":0},"frame":true},{"alpha":0.1015625,"matrix":{"c":-1,"b":1,"d":0,"tx":106.5,"ty":2.5,"a":0},"frame":true}],"instance34":[{"frame":true,"x":0,"scaleX":1,"alpha":1,"y":0,"scaleY":1,"matrix":{"c":0,"b":0,"d":1,"tx":0,"ty":0,"a":1},"rotation":0}],"instance60":[{"frame":true,"x":0,"scaleX":1,"alpha":0,"y":2,"scaleY":2.00140380859375,"matrix":{"c":0,"b":0,"d":2.00140380859375,"tx":0,"ty":2,"a":1},"rotation":0},{"alpha":0.109375,"matrix":{"c":0,"b":0,"d":2.00140380859375,"tx":0,"ty":2,"a":1},"frame":true},{"alpha":0.22265625,"matrix":{"c":0,"b":0,"d":2.00140380859375,"tx":0,"ty":2,"a":1},"frame":true},{"alpha":0.33203125,"matrix":{"c":0,"b":0,"d":2.00140380859375,"tx":0,"ty":2,"a":1},"frame":true},{"alpha":0.4453125,"matrix":{"c":0,"b":0,"d":2.00140380859375,"tx":0,"ty":2,"a":1},"frame":true},{"alpha":0.5546875,"matrix":{"c":0,"b":0,"d":2.00140380859375,"tx":0,"ty":2,"a":1},"frame":true},{"alpha":0.66796875,"matrix":{"c":0,"b":0,"d":2.00140380859375,"tx":0,"ty":2,"a":1},"frame":true},{"alpha":0.77734375,"matrix":{"c":0,"b":0,"d":2.00140380859375,"tx":0,"ty":2,"a":1},"frame":true},{"alpha":0.890625,"matrix":{"c":0,"b":0,"d":2.00140380859375,"tx":0,"ty":2,"a":1},"frame":true},{"alpha":1,"matrix":{"c":0,"b":0,"d":2.00140380859375,"tx":0,"ty":2,"a":1},"frame":true},{"alpha":0.8984375,"matrix":{"c":0,"b":0,"d":2.00140380859375,"tx":0,"ty":2,"a":1},"frame":true},{"alpha":0.80078125,"matrix":{"c":0,"b":0,"d":2.00140380859375,"tx":0,"ty":2,"a":1},"frame":true},{"alpha":0.69921875,"matrix":{"c":0,"b":0,"d":2.00140380859375,"tx":0,"ty":2,"a":1},"frame":true},{"alpha":0.6015625,"matrix":{"c":0,"b":0,"d":2.00140380859375,"tx":0,"ty":2,"a":1},"frame":true},{"alpha":0.5,"matrix":{"c":0,"b":0,"d":2.00140380859375,"tx":0,"ty":2,"a":1},"frame":true},{"alpha":0.3984375,"matrix":{"c":0,"b":0,"d":2.00140380859375,"tx":0,"ty":2,"a":1},"frame":true},{"alpha":0.30078125,"matrix":{"c":0,"b":0,"d":2.00140380859375,"tx":0,"ty":2,"a":1},"frame":true},{"alpha":0.19921875,"matrix":{"c":0,"b":0,"d":2.00140380859375,"tx":0,"ty":2,"a":1},"frame":true},{"alpha":0.1015625,"matrix":{"c":0,"b":0,"d":2.00140380859375,"tx":0,"ty":2,"a":1},"frame":true}],"instance87":[{"frame":true,"x":0,"scaleX":1,"alpha":1,"y":0,"scaleY":1,"matrix":{"c":0,"b":0,"d":1,"tx":0,"ty":0,"a":1},"rotation":0}],"instance32":[{"frame":true,"x":0,"scaleX":1,"alpha":1,"y":0,"scaleY":1,"matrix":{"c":0,"b":0,"d":1,"tx":0,"ty":0,"a":1},"rotation":0}],"instance81":[{"frame":true,"x":0,"scaleX":1,"alpha":1,"y":0,"scaleY":1,"matrix":{"c":0,"b":0,"d":1,"tx":0,"ty":0,"a":1},"rotation":0}],"instance53":[{"frame":true,"x":108,"scaleX":1,"alpha":0,"y":108,"scaleY":1,"matrix":{"c":0,"b":0,"d":-1,"tx":108.6,"ty":108,"a":-1},"rotation":180},{"alpha":0.109375,"matrix":{"c":0,"b":0,"d":-1,"tx":108.6,"ty":108,"a":-1},"frame":true},{"alpha":0.22265625,"matrix":{"c":0,"b":0,"d":-1,"tx":108.6,"ty":108,"a":-1},"frame":true},{"alpha":0.33203125,"matrix":{"c":0,"b":0,"d":-1,"tx":108.6,"ty":108,"a":-1},"frame":true},{"alpha":0.4453125,"matrix":{"c":0,"b":0,"d":-1,"tx":108.6,"ty":108,"a":-1},"frame":true},{"alpha":0.5546875,"matrix":{"c":0,"b":0,"d":-1,"tx":108.6,"ty":108,"a":-1},"frame":true},{"alpha":0.66796875,"matrix":{"c":0,"b":0,"d":-1,"tx":108.6,"ty":108,"a":-1},"frame":true},{"alpha":0.77734375,"matrix":{"c":0,"b":0,"d":-1,"tx":108.6,"ty":108,"a":-1},"frame":true},{"alpha":0.890625,"matrix":{"c":0,"b":0,"d":-1,"tx":108.6,"ty":108,"a":-1},"frame":true},{"alpha":1,"matrix":{"c":0,"b":0,"d":-1,"tx":108.6,"ty":108,"a":-1},"frame":true},{"alpha":0.8984375,"matrix":{"c":0,"b":0,"d":-1,"tx":108.6,"ty":108,"a":-1},"frame":true},{"alpha":0.80078125,"matrix":{"c":0,"b":0,"d":-1,"tx":108.6,"ty":108,"a":-1},"frame":true},{"alpha":0.69921875,"matrix":{"c":0,"b":0,"d":-1,"tx":108.6,"ty":108,"a":-1},"frame":true},{"alpha":0.6015625,"matrix":{"c":0,"b":0,"d":-1,"tx":108.6,"ty":108,"a":-1},"frame":true},{"alpha":0.5,"matrix":{"c":0,"b":0,"d":-1,"tx":108.6,"ty":108,"a":-1},"frame":true},{"alpha":0.3984375,"matrix":{"c":0,"b":0,"d":-1,"tx":108.6,"ty":108,"a":-1},"frame":true},{"alpha":0.30078125,"matrix":{"c":0,"b":0,"d":-1,"tx":108.6,"ty":108,"a":-1},"frame":true},{"alpha":0.19921875,"matrix":{"c":0,"b":0,"d":-1,"tx":108.6,"ty":108,"a":-1},"frame":true},{"alpha":0.1015625,"matrix":{"c":0,"b":0,"d":-1,"tx":108.6,"ty":108,"a":-1},"frame":true}],"instance89":[{"frame":true,"x":0,"scaleX":1,"alpha":1,"y":0,"scaleY":1,"matrix":{"c":0,"b":0,"d":1,"tx":0,"ty":0,"a":1},"rotation":0}],"instance83":[{"frame":true,"x":0,"scaleX":1,"alpha":1,"y":0,"scaleY":1,"matrix":{"c":0,"b":0,"d":1,"tx":0,"ty":0,"a":1},"rotation":0}],"instance62":[{"frame":true,"x":108,"scaleX":1,"alpha":0,"y":213,"scaleY":1.9919586181640625,"matrix":{"c":0,"b":0,"d":-1.9919586181640625,"tx":108.6,"ty":213.1,"a":-1},"rotation":180},{"frame":true,"alpha":0.109375,"matrix":{"c":0,"b":0,"d":-1.9919281005859375,"tx":108.6,"ty":213.05,"a":-1},"scaleY":1.9919281005859375},{"alpha":0.22265625,"matrix":{"c":0,"b":0,"d":-1.9919281005859375,"tx":108.6,"ty":213.05,"a":-1},"frame":true},{"alpha":0.33203125,"matrix":{"c":0,"b":0,"d":-1.9919281005859375,"tx":108.6,"ty":213.05,"a":-1},"frame":true},{"alpha":0.4453125,"matrix":{"c":0,"b":0,"d":-1.9919281005859375,"tx":108.6,"ty":213.05,"a":-1},"frame":true},{"frame":true,"alpha":0.5546875,"matrix":{"c":0,"b":0,"d":-1.9918975830078125,"tx":108.6,"ty":213.05,"a":-1},"scaleY":1.9918975830078125},{"alpha":0.66796875,"matrix":{"c":0,"b":0,"d":-1.9918975830078125,"tx":108.6,"ty":213.05,"a":-1},"frame":true},{"alpha":0.77734375,"matrix":{"c":0,"b":0,"d":-1.9918975830078125,"tx":108.6,"ty":213.05,"a":-1},"frame":true},{"alpha":0.890625,"matrix":{"c":0,"b":0,"d":-1.9918975830078125,"tx":108.6,"ty":213.05,"a":-1},"frame":true},{"frame":true,"alpha":1,"matrix":{"c":0,"b":0,"d":-1.991943359375,"tx":108.6,"ty":213.1,"a":-1},"scaleY":1.991943359375},{"alpha":0.8984375,"matrix":{"c":0,"b":0,"d":-1.991943359375,"tx":108.6,"ty":213.1,"a":-1},"frame":true},{"alpha":0.80078125,"matrix":{"c":0,"b":0,"d":-1.991943359375,"tx":108.6,"ty":213.1,"a":-1},"frame":true},{"alpha":0.69921875,"matrix":{"c":0,"b":0,"d":-1.991943359375,"tx":108.6,"ty":213.1,"a":-1},"frame":true},{"alpha":0.6015625,"matrix":{"c":0,"b":0,"d":-1.991943359375,"tx":108.6,"ty":213.1,"a":-1},"frame":true},{"alpha":0.5,"matrix":{"c":0,"b":0,"d":-1.991943359375,"tx":108.6,"ty":213.1,"a":-1},"frame":true},{"alpha":0.3984375,"matrix":{"c":0,"b":0,"d":-1.991943359375,"tx":108.6,"ty":213.1,"a":-1},"frame":true},{"alpha":0.30078125,"matrix":{"c":0,"b":0,"d":-1.991943359375,"tx":108.6,"ty":213.1,"a":-1},"frame":true},{"alpha":0.19921875,"matrix":{"c":0,"b":0,"d":-1.991943359375,"tx":108.6,"ty":213.1,"a":-1},"frame":true},{"alpha":0.1015625,"matrix":{"c":0,"b":0,"d":-1.991943359375,"tx":108.6,"ty":213.1,"a":-1},"frame":true}],"instance57":[{"frame":true,"x":106,"scaleX":1,"alpha":0,"y":2,"scaleY":1,"matrix":{"c":-1,"b":1,"d":0,"tx":106.5,"ty":2.5,"a":0},"rotation":90},{"alpha":0.109375,"matrix":{"c":-1,"b":1,"d":0,"tx":106.5,"ty":2.5,"a":0},"frame":true},{"alpha":0.22265625,"matrix":{"c":-1,"b":1,"d":0,"tx":106.5,"ty":2.5,"a":0},"frame":true},{"alpha":0.33203125,"matrix":{"c":-1,"b":1,"d":0,"tx":106.5,"ty":2.5,"a":0},"frame":true},{"alpha":0.4453125,"matrix":{"c":-1,"b":1,"d":0,"tx":106.5,"ty":2.5,"a":0},"frame":true},{"alpha":0.5546875,"matrix":{"c":-1,"b":1,"d":0,"tx":106.5,"ty":2.5,"a":0},"frame":true},{"alpha":0.66796875,"matrix":{"c":-1,"b":1,"d":0,"tx":106.5,"ty":2.5,"a":0},"frame":true},{"alpha":0.77734375,"matrix":{"c":-1,"b":1,"d":0,"tx":106.5,"ty":2.5,"a":0},"frame":true},{"alpha":0.890625,"matrix":{"c":-1,"b":1,"d":0,"tx":106.5,"ty":2.5,"a":0},"frame":true},{"alpha":1,"matrix":{"c":-1,"b":1,"d":0,"tx":106.5,"ty":2.5,"a":0},"frame":true},{"alpha":0.8984375,"matrix":{"c":-1,"b":1,"d":0,"tx":106.5,"ty":2.5,"a":0},"frame":true},{"alpha":0.80078125,"matrix":{"c":-1,"b":1,"d":0,"tx":106.5,"ty":2.5,"a":0},"frame":true},{"alpha":0.69921875,"matrix":{"c":-1,"b":1,"d":0,"tx":106.5,"ty":2.5,"a":0},"frame":true},{"alpha":0.6015625,"matrix":{"c":-1,"b":1,"d":0,"tx":106.5,"ty":2.5,"a":0},"frame":true},{"alpha":0.5,"matrix":{"c":-1,"b":1,"d":0,"tx":106.5,"ty":2.5,"a":0},"frame":true},{"alpha":0.3984375,"matrix":{"c":-1,"b":1,"d":0,"tx":106.5,"ty":2.5,"a":0},"frame":true},{"alpha":0.30078125,"matrix":{"c":-1,"b":1,"d":0,"tx":106.5,"ty":2.5,"a":0},"frame":true},{"alpha":0.19921875,"matrix":{"c":-1,"b":1,"d":0,"tx":106.5,"ty":2.5,"a":0},"frame":true},{"alpha":0.1015625,"matrix":{"c":-1,"b":1,"d":0,"tx":106.5,"ty":2.5,"a":0},"frame":true}],"instance64":[{"frame":true,"x":0,"scaleX":1,"alpha":0,"y":215,"scaleY":1,"matrix":{"c":1,"b":-1,"d":0,"tx":0,"ty":215,"a":0},"rotation":-90},{"alpha":0.109375,"matrix":{"c":1,"b":-1,"d":0,"tx":0,"ty":215,"a":0},"frame":true},{"alpha":0.22265625,"matrix":{"c":1,"b":-1,"d":0,"tx":0,"ty":215,"a":0},"frame":true},{"alpha":0.33203125,"matrix":{"c":1,"b":-1,"d":0,"tx":0,"ty":215,"a":0},"frame":true},{"alpha":0.4453125,"matrix":{"c":1,"b":-1,"d":0,"tx":0,"ty":215,"a":0},"frame":true},{"alpha":0.5546875,"matrix":{"c":1,"b":-1,"d":0,"tx":0,"ty":215,"a":0},"frame":true},{"alpha":0.66796875,"matrix":{"c":1,"b":-1,"d":0,"tx":0,"ty":215,"a":0},"frame":true},{"alpha":0.77734375,"matrix":{"c":1,"b":-1,"d":0,"tx":0,"ty":215,"a":0},"frame":true},{"alpha":0.890625,"matrix":{"c":1,"b":-1,"d":0,"tx":0,"ty":215,"a":0},"frame":true},{"alpha":1,"matrix":{"c":1,"b":-1,"d":0,"tx":0,"ty":215,"a":0},"frame":true},{"alpha":0.8984375,"matrix":{"c":1,"b":-1,"d":0,"tx":0,"ty":215,"a":0},"frame":true},{"alpha":0.80078125,"matrix":{"c":1,"b":-1,"d":0,"tx":0,"ty":215,"a":0},"frame":true},{"alpha":0.69921875,"matrix":{"c":1,"b":-1,"d":0,"tx":0,"ty":215,"a":0},"frame":true},{"alpha":0.6015625,"matrix":{"c":1,"b":-1,"d":0,"tx":0,"ty":215,"a":0},"frame":true},{"alpha":0.5,"matrix":{"c":1,"b":-1,"d":0,"tx":0,"ty":215,"a":0},"frame":true},{"alpha":0.3984375,"matrix":{"c":1,"b":-1,"d":0,"tx":0,"ty":215,"a":0},"frame":true},{"alpha":0.30078125,"matrix":{"c":1,"b":-1,"d":0,"tx":0,"ty":215,"a":0},"frame":true},{"alpha":0.19921875,"matrix":{"c":1,"b":-1,"d":0,"tx":0,"ty":215,"a":0},"frame":true},{"alpha":0.1015625,"matrix":{"c":1,"b":-1,"d":0,"tx":0,"ty":215,"a":0},"frame":true}],"instance51":[{"frame":true,"x":0,"scaleX":1,"alpha":0,"y":2,"scaleY":1,"matrix":{"c":0,"b":0,"d":1,"tx":0,"ty":2,"a":1},"rotation":0},{"alpha":0.109375,"matrix":{"c":0,"b":0,"d":1,"tx":0,"ty":2,"a":1},"frame":true},{"alpha":0.22265625,"matrix":{"c":0,"b":0,"d":1,"tx":0,"ty":2,"a":1},"frame":true},{"alpha":0.33203125,"matrix":{"c":0,"b":0,"d":1,"tx":0,"ty":2,"a":1},"frame":true},{"alpha":0.4453125,"matrix":{"c":0,"b":0,"d":1,"tx":0,"ty":2,"a":1},"frame":true},{"alpha":0.5546875,"matrix":{"c":0,"b":0,"d":1,"tx":0,"ty":2,"a":1},"frame":true},{"alpha":0.66796875,"matrix":{"c":0,"b":0,"d":1,"tx":0,"ty":2,"a":1},"frame":true},{"alpha":0.77734375,"matrix":{"c":0,"b":0,"d":1,"tx":0,"ty":2,"a":1},"frame":true},{"alpha":0.890625,"matrix":{"c":0,"b":0,"d":1,"tx":0,"ty":2,"a":1},"frame":true},{"alpha":1,"matrix":{"c":0,"b":0,"d":1,"tx":0,"ty":2,"a":1},"frame":true},{"alpha":0.8984375,"matrix":{"c":0,"b":0,"d":1,"tx":0,"ty":2,"a":1},"frame":true},{"alpha":0.80078125,"matrix":{"c":0,"b":0,"d":1,"tx":0,"ty":2,"a":1},"frame":true},{"alpha":0.69921875,"matrix":{"c":0,"b":0,"d":1,"tx":0,"ty":2,"a":1},"frame":true},{"alpha":0.6015625,"matrix":{"c":0,"b":0,"d":1,"tx":0,"ty":2,"a":1},"frame":true},{"alpha":0.5,"matrix":{"c":0,"b":0,"d":1,"tx":0,"ty":2,"a":1},"frame":true},{"alpha":0.3984375,"matrix":{"c":0,"b":0,"d":1,"tx":0,"ty":2,"a":1},"frame":true},{"alpha":0.30078125,"matrix":{"c":0,"b":0,"d":1,"tx":0,"ty":2,"a":1},"frame":true},{"alpha":0.19921875,"matrix":{"c":0,"b":0,"d":1,"tx":0,"ty":2,"a":1},"frame":true},{"alpha":0.1015625,"matrix":{"c":0,"b":0,"d":1,"tx":0,"ty":2,"a":1},"frame":true}],"instance69":[{"frame":true,"x":0,"scaleX":1,"alpha":1,"y":0,"scaleY":1,"matrix":{"c":0,"b":0,"d":1,"tx":0,"ty":0,"a":1},"rotation":0}],"instance75":[{"frame":true,"x":0,"scaleX":1,"alpha":1,"y":0,"scaleY":1,"matrix":{"c":0,"b":0,"d":1,"tx":0,"ty":0,"a":1},"rotation":0}]},"stage":{"children":[{"x":870.95,"type":"asset","instanceName":"instance4","alpha":1,"y":231.5,"name":"Symbol9","matrix":{"c":0,"b":0,"d":1,"tx":870.95,"ty":231.5,"a":1},"template":true},{"x":980.95,"type":"asset","instanceName":"instance6","alpha":1,"y":229.5,"name":"Symbol13","matrix":{"c":0,"b":0,"d":1,"tx":980.95,"ty":229.5,"a":1},"template":true},{"x":868.95,"type":"asset","instanceName":"instance8","alpha":1,"y":340.5,"name":"Symbol3","matrix":{"c":0,"b":0,"d":1,"tx":868.95,"ty":340.5,"a":1},"template":true},{"x":647.95,"type":"asset","instanceName":"instance10","alpha":1,"y":339.5,"name":"Symbol12","matrix":{"c":0,"b":0,"d":1,"tx":647.95,"ty":339.5,"a":1},"template":true},{"x":1090.95,"type":"asset","instanceName":"instance12","alpha":1,"y":234.55,"name":"Symbol1","matrix":{"c":0,"b":0,"d":1,"tx":1090.95,"ty":234.55,"a":1},"template":true},{"x":980.95,"type":"asset","instanceName":"instance14","alpha":1,"y":119.5,"name":"Symbol2","matrix":{"c":0,"b":0,"d":1,"tx":980.95,"ty":119.5,"a":1},"template":true},{"x":1090.95,"type":"asset","instanceName":"instance16","alpha":1,"y":124.55,"name":"Symbol7","matrix":{"c":0,"b":0,"d":1,"tx":1090.95,"ty":124.55,"a":1},"template":true},{"x":870.95,"type":"asset","instanceName":"instance18","alpha":1,"y":119.5,"name":"Symbol8","matrix":{"c":0,"b":0,"d":1,"tx":870.95,"ty":119.5,"a":1},"template":true},{"x":758.95,"type":"asset","instanceName":"instance20","alpha":1,"y":339.5,"name":"Symbol6","matrix":{"c":0,"b":0,"d":1,"tx":758.95,"ty":339.5,"a":1},"template":true},{"x":758.95,"type":"asset","instanceName":"instance22","alpha":1,"y":124.55,"name":"Symbol4","matrix":{"c":0,"b":0,"d":1,"tx":758.95,"ty":124.55,"a":1},"template":true},{"x":758.95,"type":"asset","instanceName":"instance24","alpha":1,"y":234.55,"name":"Symbol5","matrix":{"c":0,"b":0,"d":1,"tx":758.95,"ty":234.55,"a":1},"template":true},{"x":647.95,"type":"asset","instanceName":"instance26","alpha":1,"y":229.5,"name":"Symbol11","matrix":{"c":0,"b":0,"d":1,"tx":647.95,"ty":229.5,"a":1},"template":true},{"x":0,"type":"asset","instanceName":"instance28","alpha":1,"y":7.5,"name":"SlotMachineMC","matrix":{"c":0,"b":0,"d":1,"tx":0,"ty":7.5,"a":1},"template":true},{"x":648.95,"type":"asset","instanceName":"instance48","alpha":1,"y":121.55,"name":"Symbol10","matrix":{"c":0,"b":0,"d":1,"tx":648.95,"ty":121.55,"a":1},"template":true},{"x":946.95,"type":"asset","instanceName":"instance50","alpha":1,"y":474.4,"name":"Highlight1x1","matrix":{"c":0,"b":0,"d":1,"tx":946.95,"ty":474.4,"a":1},"template":true},{"x":1116.15,"type":"asset","instanceName":"instance59","alpha":1,"y":379.05,"name":"Highlight1x2","matrix":{"c":0,"b":0,"d":1,"tx":1116.15,"ty":379.05,"a":1},"template":true}]},"templates":{"Symbol9":{"type":"asset","children":[{"x":0,"type":"img","height":110,"name":"Symbol9_IMG","y":0,"width":110}],"template":true,"name":"Symbol9"},"PaysUp":{"type":"asset","children":[{"x":0,"type":"img","height":37,"name":"PaysUp_IMG","y":0,"width":62}],"template":true,"name":"PaysUp"},"Symbol11":{"type":"asset","children":[{"x":0,"type":"img","height":110,"name":"Symbol11_IMG","y":0,"width":110}],"template":true,"name":"Symbol11"},"ReelsContainer":{"type":"asset","children":[{"x":0,"type":"asset","instanceName":"reel1","alpha":1,"y":0,"name":"ReelMC","matrix":{"c":0,"b":0,"d":1,"tx":0,"ty":0,"a":1},"template":true},{"x":110,"type":"asset","instanceName":"reel2","alpha":1,"y":0,"name":"ReelMC","matrix":{"c":0,"b":0,"d":1,"tx":110,"ty":0,"a":1},"template":true},{"x":220,"type":"asset","instanceName":"reel3","alpha":1,"y":0,"name":"ReelMC","matrix":{"c":0,"b":0,"d":1,"tx":220,"ty":0,"a":1},"template":true},{"x":330,"type":"asset","instanceName":"reel4","alpha":1,"y":0,"name":"ReelMC","matrix":{"c":0,"b":0,"d":1,"tx":330,"ty":0,"a":1},"template":true},{"x":440,"type":"asset","instanceName":"reel5","alpha":1,"y":0,"name":"ReelMC","matrix":{"c":0,"b":0,"d":1,"tx":440,"ty":0,"a":1},"template":true}],"template":true,"name":"ReelsContainer"},"Symbol8":{"type":"asset","children":[{"x":0,"type":"img","height":110,"name":"Symbol8_IMG","y":0,"width":110}],"template":true,"name":"Symbol8"},"Symbol3":{"type":"asset","children":[{"x":0,"type":"img","height":110,"name":"Symbol3_IMG","y":0,"width":110}],"template":true,"name":"Symbol3"},"Symbol12":{"type":"asset","children":[{"x":0,"type":"img","height":110,"name":"Symbol12_IMG","y":0,"width":110}],"template":true,"name":"Symbol12"},"HighlightLineMC":{"type":"asset","children":[{"x":0,"type":"img","height":106,"name":"HighlightLineMC_IMG","y":0,"width":25}],"template":true,"name":"HighlightLineMC"},"ReelMC":{"type":"asset","children":[{"x":0,"type":"asset","instanceName":"instance46","alpha":0.08984375,"y":0,"name":"EmptyItem","matrix":{"c":0,"b":0,"d":1,"tx":0,"ty":0,"a":1},"template":true}],"template":true,"name":"ReelMC"},"Symbol7":{"type":"asset","children":[{"x":0,"type":"img","height":110,"name":"Symbol7_IMG","y":0,"width":110}],"template":true,"name":"Symbol7"},"Highlight1x1":{"type":"asset","children":[{"x":0,"type":"asset","instanceName":"instance51","alpha":0,"y":2,"name":"HighlightLineMC","matrix":{"c":0,"b":0,"d":1,"tx":0,"ty":2,"a":1},"template":true},{"x":108.6,"type":"asset","instanceName":"instance53","alpha":0,"y":108,"name":"HighlightLineMC","matrix":{"c":0,"b":0,"d":-1,"tx":108.6,"ty":108,"a":-1},"template":true},{"x":0,"type":"asset","instanceName":"instance55","alpha":0,"y":108,"name":"HighlightLineMC","matrix":{"c":1,"b":-1,"d":0,"tx":0,"ty":108,"a":0},"template":true},{"x":106.5,"type":"asset","instanceName":"instance57","alpha":0,"y":2.5,"name":"HighlightLineMC","matrix":{"c":-1,"b":1,"d":0,"tx":106.5,"ty":2.5,"a":0},"template":true}],"template":true,"name":"Highlight1x1"},"Symbol10":{"type":"asset","children":[{"x":0,"type":"img","height":110,"name":"Symbol10_IMG","y":0,"width":110}],"template":true,"name":"Symbol10"},"Highlight1x2":{"type":"asset","children":[{"x":0,"type":"asset","instanceName":"instance60","alpha":0,"y":2,"name":"HighlightLineMC","matrix":{"c":0,"b":0,"d":2.00140380859375,"tx":0,"ty":2,"a":1},"template":true},{"x":108.6,"type":"asset","instanceName":"instance62","alpha":0,"y":213.1,"name":"HighlightLineMC","matrix":{"c":0,"b":0,"d":-1.9919586181640625,"tx":108.6,"ty":213.1,"a":-1},"template":true},{"x":0,"type":"asset","instanceName":"instance64","alpha":0,"y":215,"name":"HighlightLineMC","matrix":{"c":1,"b":-1,"d":0,"tx":0,"ty":215,"a":0},"template":true},{"x":106.5,"type":"asset","instanceName":"instance66","alpha":0,"y":2.5,"name":"HighlightLineMC","matrix":{"c":-1,"b":1,"d":0,"tx":106.5,"ty":2.5,"a":0},"template":true}],"template":true,"name":"Highlight1x2"},"PlusUP":{"type":"asset","children":[{"x":0,"type":"img","height":48,"name":"PlusUP_IMG","y":0,"width":70}],"template":true,"name":"PlusUP"},"EmptyItem":{"type":"asset","children":[{"x":0,"type":"img","height":48,"name":"EmptyItem_IMG","y":0,"width":48}],"template":true,"name":"EmptyItem"},"Symbol1":{"type":"asset","children":[{"x":0,"type":"img","height":110,"name":"Symbol1_IMG","y":0,"width":110}],"template":true,"name":"Symbol1"},"PaysBTN":{"x":190.05,"type":"btn","instanceName":"paysBTN","alpha":1,"y":541,"name":"PaysBTN","children":[{"x":0,"type":"asset","instanceName":"instance32","alpha":1,"y":0,"name":"PaysUp","matrix":{"c":0,"b":0,"d":1,"tx":0,"ty":0,"a":1},"template":true}],"matrix":{"c":0,"b":0,"d":1,"tx":190.05,"ty":541,"a":1},"template":true},"Symbol2":{"type":"asset","children":[{"x":0,"type":"img","height":110,"name":"Symbol2_IMG","y":0,"width":110}],"template":true,"name":"Symbol2"},"Symbol13":{"type":"asset","children":[{"x":0,"type":"img","height":220,"name":"Symbol13_IMG","y":0,"width":110}],"template":true,"name":"Symbol13"},"SpinBTN":{"x":474.05,"type":"btn","instanceName":"spinBTN","alpha":1,"y":474,"name":"SpinBTN","children":[{"x":0,"type":"asset","instanceName":"instance36","alpha":1,"y":0,"name":"SpinUp","matrix":{"c":0,"b":0,"d":1,"tx":0,"ty":0,"a":1},"template":true}],"matrix":{"c":0,"b":0,"d":1,"tx":474.05,"ty":474,"a":1},"template":true},"Symbol6":{"type":"asset","children":[{"x":0,"type":"img","height":110,"name":"Symbol6_IMG","y":0,"width":110}],"template":true,"name":"Symbol6"},"SlotMachineMC":{"type":"asset","children":[{"x":0,"type":"asset","instanceName":"slotMC","alpha":1,"y":0,"name":"SlotMC","matrix":{"c":0,"b":0,"d":1,"tx":0,"ty":0,"a":1},"template":true},{"x":362.05,"type":"btn","instanceName":"minusBTN","alpha":1,"y":534,"name":"minusBTN","children":[{"x":0,"type":"asset","instanceName":"instance30","alpha":1,"y":0,"name":"MinusUp","matrix":{"c":0,"b":0,"d":1,"tx":0,"ty":0,"a":1},"template":true}],"matrix":{"c":0,"b":0,"d":1,"tx":362.05,"ty":534,"a":1},"template":false},{"x":190.05,"type":"btn","instanceName":"paysBTN","alpha":1,"y":541,"name":"PaysBTN","children":[{"x":0,"type":"asset","instanceName":"instance32","alpha":1,"y":0,"name":"PaysUp","matrix":{"c":0,"b":0,"d":1,"tx":0,"ty":0,"a":1},"template":true}],"matrix":{"c":0,"b":0,"d":1,"tx":190.05,"ty":541,"a":1},"template":true},{"x":292.45,"type":"btn","instanceName":"plusBTN","alpha":1,"y":536,"name":"PlusBTN","children":[{"x":0,"type":"asset","instanceName":"instance34","alpha":1,"y":0,"name":"PlusUP","matrix":{"c":0,"b":0,"d":1,"tx":0,"ty":0,"a":1},"template":true}],"matrix":{"c":0,"b":0,"d":1,"tx":292.45,"ty":536,"a":1},"template":true},{"x":474.05,"type":"btn","instanceName":"spinBTN","alpha":1,"y":474,"name":"SpinBTN","children":[{"x":0,"type":"asset","instanceName":"instance36","alpha":1,"y":0,"name":"SpinUp","matrix":{"c":0,"b":0,"d":1,"tx":0,"ty":0,"a":1},"template":true}],"matrix":{"c":0,"b":0,"d":1,"tx":474.05,"ty":474,"a":1},"template":true},{"x":34,"type":"asset","instanceName":"reelsContainerMC","alpha":1,"y":114.05,"name":"ReelsContainer","matrix":{"c":0,"b":0,"d":1,"tx":34,"ty":114.05,"a":1},"template":true}],"template":true,"name":"SlotMachineMC"},"Symbol5":{"type":"asset","children":[{"x":0,"type":"img","height":110,"name":"Symbol5_IMG","y":0,"width":110}],"template":true,"name":"Symbol5"},"SpinUp":{"type":"asset","children":[{"x":0,"type":"img","height":118,"name":"SpinUp_IMG","y":0,"width":121}],"template":true,"name":"SpinUp"},"PlusBTN":{"x":292.45,"type":"btn","instanceName":"plusBTN","alpha":1,"y":536,"name":"PlusBTN","children":[{"x":0,"type":"asset","instanceName":"instance34","alpha":1,"y":0,"name":"PlusUP","matrix":{"c":0,"b":0,"d":1,"tx":0,"ty":0,"a":1},"template":true}],"matrix":{"c":0,"b":0,"d":1,"tx":292.45,"ty":536,"a":1},"template":true},"minusBTN":{"x":362.05,"type":"btn","instanceName":"minusBTN","alpha":1,"y":534,"name":"minusBTN","children":[{"x":0,"type":"asset","instanceName":"instance30","alpha":1,"y":0,"name":"MinusUp","matrix":{"c":0,"b":0,"d":1,"tx":0,"ty":0,"a":1},"template":true}],"matrix":{"c":0,"b":0,"d":1,"tx":362.05,"ty":534,"a":1},"template":false},"MinusUp":{"type":"asset","children":[{"x":0,"type":"img","height":50,"name":"MinusUp_IMG","y":0,"width":68}],"template":true,"name":"MinusUp"},"SlotMC":{"type":"asset","children":[{"x":0,"type":"img","height":614,"name":"SlotMC_IMG","y":0,"width":622}],"template":true,"name":"SlotMC"},"Symbol4":{"type":"asset","children":[{"x":0,"type":"img","height":110,"name":"Symbol4_IMG","y":0,"width":110}],"template":true,"name":"Symbol4"}}}